sthreepo
