Metadata-Version: 2.1
Name: sthreepo
Version: 0.0.2
Summary: Simple Debian repository manager using S3
Home-page: https://github.com/juitnow/sthreepo
Author: Juit Developers
Author-email: developers@juit.com
Maintainer: Juit Developers
Maintainer-email: developers@juit.com
License: Apache-2.0
Keywords: AWS,DEB,Debian,Repository,S3
Platform: UNKNOWN
Classifier: Topic :: System :: Operating System
Classifier: Topic :: System :: Software Distribution
Classifier: Topic :: System :: Systems Administration
Classifier: Development Status :: 3 - Alpha
Classifier: License :: OSI Approved :: Apache Software License
Classifier: Programming Language :: Python :: 3
Classifier: Intended Audience :: Developers
Classifier: Intended Audience :: System Administrators
Requires-Python: >=3.5
License-File: LICENSE.md
License-File: NOTICE.md
